codebubble/__init__.py
codebubble/utils.py
codebubble/executor/__init__.py
codebubble/executor/base.py
codebubble/executor/cpp.py
codebubble/executor/python.py
codebubble/sandbox/__init__.py
codebubble/sandbox/base.py
codebubble/sandbox/bwrap.py
codebubble-0.1.0.dist-info/licenses/LICENSE
codebubble-0.1.0.dist-info/METADATA
codebubble-0.1.0.dist-info/WHEEL
codebubble-0.1.0.dist-info/top_level.txt
codebubble-0.1.0.dist-info/RECORD
