Metadata-Version: 2.4
Name: codebubble
Version: 0.1.0
Summary: Rootless sandbox for running untrusted code
Home-page: https://github.com/twelfth-star/codebubble
Author: Morris He
Author-email: hzm20021210@gmail.com
License: MIT
Classifier: Programming Language :: Python :: 3
Classifier: License :: OSI Approved :: MIT License
Classifier: Operating System :: POSIX :: Linux
Requires-Python: >=3.7
License-File: LICENSE
Requires-Dist: pydantic>=1.10.0
Requires-Dist: loguru>=0.6.0
Dynamic: author
Dynamic: author-email
Dynamic: classifier
Dynamic: description
Dynamic: description-content-type
Dynamic: home-page
Dynamic: license
Dynamic: license-file
Dynamic: requires-dist
Dynamic: requires-python
Dynamic: summary
